[
  { "id": "nl-30", "timestamp": "2026-07-17T08:45:12", "eventType": "gunshot", "channel": "line", "recipient": "กลุ่มผู้ดูแลระบบ", "message": "ตรวจพบเสียงปืนบริเวณกล้อง CAM-012 ถนนพัทยาใต้", "status": "sent" },
  { "id": "nl-29", "timestamp": "2026-07-17T08:45:10", "eventType": "gunshot", "channel": "sms", "recipient": "สุรศักดิ์ ปฏิบัติ", "message": "ตรวจพบเสียงปืนบริเวณกล้อง CAM-012 ถนนพัทยาใต้", "status": "sent" },
  { "id": "nl-28", "timestamp": "2026-07-17T08:45:08", "eventType": "gunshot", "channel": "email", "recipient": "thana@chonburi.go.th", "message": "ตรวจพบเสียงปืนบริเวณกล้อง CAM-012 ถนนพัทยาใต้", "status": "failed" },
  { "id": "nl-27", "timestamp": "2026-07-17T07:30:45", "eventType": "traffic", "channel": "line", "recipient": "กลุ่มเจ้าหน้าที่ควบคุม", "message": "การจราจรหนาแน่นบริเวณกล้อง CAM-003 แยกบางแสน", "status": "sent" },
  { "id": "nl-26", "timestamp": "2026-07-17T07:15:20", "eventType": "traffic", "channel": "line", "recipient": "กลุ่มผู้ดูแลระบบ", "message": "การจราจรหนาแน่นบริเวณกล้อง CAM-021 ถนนสุขุมวิท ขาเข้าเมืองชลบุรี", "status": "sent" },
  { "id": "nl-25", "timestamp": "2026-07-16T22:10:05", "eventType": "crowd", "channel": "email", "recipient": "กลุ่มผู้ดูแลระบบ", "message": "ตรวจพบการรวมตัวของฝูงชนบริเวณกล้อง CAM-018 ถนนข้าวหลาม", "status": "sent" },
  { "id": "nl-24", "timestamp": "2026-07-16T22:10:03", "eventType": "crowd", "channel": "line", "recipient": "กลุ่มเจ้าหน้าที่ควบคุม", "message": "ตรวจพบการรวมตัวของฝูงชนบริเวณกล้อง CAM-018 ถนนข้าวหลาม", "status": "sent" },
  { "id": "nl-23", "timestamp": "2026-07-16T18:05:44", "eventType": "parking", "channel": "line", "recipient": "กลุ่มผู้ดูแลระบบ", "message": "ตรวจพบการจอดรถผิดกฎหมายบริเวณกล้อง CAM-007 หน้าตลาดหนองมน", "status": "sent" },
  { "id": "nl-22", "timestamp": "2026-07-16T16:40:31", "eventType": "flood", "channel": "sms", "recipient": "กลุ่มผู้ดูแลระบบ", "message": "ระดับน้ำสูงผิดปกติบริเวณกล้อง CAM-009 ถนนเลียบชายหาดบางแสน", "status": "sent" },
  { "id": "nl-21", "timestamp": "2026-07-16T16:40:28", "eventType": "flood", "channel": "email", "recipient": "thana@chonburi.go.th", "message": "ระดับน้ำสูงผิดปกติบริเวณกล้อง CAM-009 ถนนเลียบชายหาดบางแสน", "status": "sent" },
  { "id": "nl-20", "timestamp": "2026-07-16T16:40:25", "eventType": "flood", "channel": "line", "recipient": "กลุ่มเจ้าหน้าที่ควบคุม", "message": "ระดับน้ำสูงผิดปกติบริเวณกล้อง CAM-009 ถนนเลียบชายหาดบางแสน", "status": "sent" },
  { "id": "nl-19", "timestamp": "2026-07-16T14:22:17", "eventType": "traffic", "channel": "line", "recipient": "กลุ่มเจ้าหน้าที่ควบคุม", "message": "การจราจรหนาแน่นบริเวณกล้อง CAM-014 แยกอ่างศิลา", "status": "failed" },
  { "id": "nl-18", "timestamp": "2026-07-16T11:50:09", "eventType": "parking", "channel": "line", "recipient": "กลุ่มผู้ดูแลระบบ", "message": "ตรวจพบการจอดรถผิดกฎหมายบริเวณกล้อง CAM-002 หน้าโรงพยาบาลชลบุรี", "status": "sent" },
  { "id": "nl-17", "timestamp": "2026-07-16T09:35:56", "eventType": "crowd", "channel": "line", "recipient": "กลุ่มผู้ดูแลระบบ", "message": "ตรวจพบการรวมตัวของฝูงชนบริเวณกล้อง CAM-025 หน้าศาลากลางจังหวัด", "status": "sent" },
  { "id": "nl-16", "timestamp": "2026-07-15T20:18:40", "eventType": "gunshot", "channel": "line", "recipient": "กลุ่มผู้ดูแลระบบ", "message": "ตรวจพบเสียงปืนบริเวณกล้อง CAM-030 ซอยเขาตาโล พัทยา", "status": "sent" },
  { "id": "nl-15", "timestamp": "2026-07-15T20:18:38", "eventType": "gunshot", "channel": "sms", "recipient": "กลุ่มผู้ดูแลระบบ", "message": "ตรวจพบเสียงปืนบริเวณกล้อง CAM-030 ซอยเขาตาโล พัทยา", "status": "failed" },
  { "id": "nl-14", "timestamp": "2026-07-15T17:02:12", "eventType": "traffic", "channel": "line", "recipient": "กลุ่มเจ้าหน้าที่ควบคุม", "message": "การจราจรหนาแน่นบริเวณกล้อง CAM-005 ถนนสุขุมวิท หน้านิคมอมตะ", "status": "sent" },
  { "id": "nl-13", "timestamp": "2026-07-15T15:47:33", "eventType": "parking", "channel": "line", "recipient": "กลุ่มผู้ดูแลระบบ", "message": "ตรวจพบการจอดรถผิดกฎหมายบริเวณกล้อง CAM-011 ถนนวชิรปราการ", "status": "sent" },
  { "id": "nl-12", "timestamp": "2026-07-15T13:29:51", "eventType": "flood", "channel": "line", "recipient": "กลุ่มเจ้าหน้าที่ควบคุม", "message": "ระดับน้ำสูงผิดปกติบริเวณกล้อง CAM-016 ตลาดใหม่ชลบุรี", "status": "sent" },
  { "id": "nl-11", "timestamp": "2026-07-15T10:14:27", "eventType": "crowd", "channel": "email", "recipient": "กลุ่มผู้ดูแลระบบ", "message": "ตรวจพบการรวมตัวของฝูงชนบริเวณกล้อง CAM-022 สวนสาธารณะบางแสน", "status": "sent" },
  { "id": "nl-10", "timestamp": "2026-07-14T21:55:03", "eventType": "gunshot", "channel": "line", "recipient": "กลุ่มผู้ดูแลระบบ", "message": "ตรวจพบเสียงปืนบริเวณกล้อง CAM-027 ถนนพัทยาเหนือ", "status": "sent" },
  { "id": "nl-9", "timestamp": "2026-07-14T19:33:48", "eventType": "traffic", "channel": "line", "recipient": "กลุ่มเจ้าหน้าที่ควบคุม", "message": "การจราจรหนาแน่นบริเวณกล้อง CAM-001 แยกเฉลิมไทย", "status": "sent" },
  { "id": "nl-8", "timestamp": "2026-07-14T16:08:22", "eventType": "parking", "channel": "line", "recipient": "กลุ่มผู้ดูแลระบบ", "message": "ตรวจพบการจอดรถผิดกฎหมายบริเวณกล้อง CAM-019 หน้าตลาดนาเกลือ", "status": "failed" },
  { "id": "nl-7", "timestamp": "2026-07-14T12:41:15", "eventType": "flood", "channel": "email", "recipient": "thana@chonburi.go.th", "message": "ระดับน้ำสูงผิดปกติบริเวณกล้อง CAM-013 ถนนพระยาสัจจา", "status": "sent" },
  { "id": "nl-6", "timestamp": "2026-07-14T09:26:59", "eventType": "crowd", "channel": "line", "recipient": "กลุ่มเจ้าหน้าที่ควบคุม", "message": "ตรวจพบการรวมตัวของฝูงชนบริเวณกล้อง CAM-024 ท่าเรือแหลมฉบัง", "status": "sent" },
  { "id": "nl-5", "timestamp": "2026-07-13T18:12:36", "eventType": "traffic", "channel": "line", "recipient": "กลุ่มเจ้าหน้าที่ควบคุม", "message": "การจราจรหนาแน่นบริเวณกล้อง CAM-008 ถนนบายพาสเลี่ยงเมือง", "status": "sent" },
  { "id": "nl-4", "timestamp": "2026-07-13T15:58:14", "eventType": "gunshot", "channel": "email", "recipient": "กลุ่มผู้ดูแลระบบ", "message": "ตรวจพบเสียงปืนบริเวณกล้อง CAM-031 ซอยบัวขาว พัทยา", "status": "sent" },
  { "id": "nl-3", "timestamp": "2026-07-13T11:37:02", "eventType": "parking", "channel": "line", "recipient": "กลุ่มผู้ดูแลระบบ", "message": "ตรวจพบการจอดรถผิดกฎหมายบริเวณกล้อง CAM-006 หน้าศูนย์ราชการ", "status": "sent" },
  { "id": "nl-2", "timestamp": "2026-07-13T08:20:47", "eventType": "flood", "channel": "line", "recipient": "กลุ่มเจ้าหน้าที่ควบคุม", "message": "ระดับน้ำสูงผิดปกติบริเวณกล้อง CAM-010 ชุมชนบ้านโขด", "status": "sent" },
  { "id": "nl-1", "timestamp": "2026-07-12T22:05:30", "eventType": "crowd", "channel": "line", "recipient": "กลุ่มผู้ดูแลระบบ", "message": "ตรวจพบการรวมตัวของฝูงชนบริเวณกล้อง CAM-020 ถนนคนเดินพัทยา", "status": "sent" }
]
